igwtools
