Metadata-Version: 1.0
Name: igwtools
Version: 0.3.dev-r412
Summary: Tools for internal gravity waves experiments
Home-page: http://www.ualberta.ca/~jmunroe/igwtools
Author: James R. Munroe
Author-email: jmunroe@ualberta.ca
License: MIT
Platform: UNKNOWN
Classifier: License :: OSI Approved
